anko/__init__.py
anko/anko.py
anko/proto/__init__.py
anko/proto/gateway_pb2.py
anko/proto/gateway_pb2_grpc.py
anko_sdk-1.2.0.dist-info/LICENCE
anko_sdk-1.2.0.dist-info/METADATA
anko_sdk-1.2.0.dist-info/WHEEL
anko_sdk-1.2.0.dist-info/top_level.txt
anko_sdk-1.2.0.dist-info/RECORD
