Metadata-Version: 2.1
Name: anko-sdk
Version: 1.2.0
Summary: Python SDK for https://anko-investor.com market forecasts. Signup today!
Home-page: https://github.com/anglo-korean/anko-python-sdk
Author: Anglo Korean
Author-email: hello@anglo-korean.com
License: UNKNOWN
Project-URL: Bug Tracker, https://github.com/anglo-korean/anko-python-sdk/issues
Platform: UNKNOWN
Classifier: Programming Language :: Python :: 3
Classifier: License :: OSI Approved :: MIT License
Classifier: Operating System :: OS Independent
Requires-Python: >=3.6
License-File: LICENCE
Requires-Dist: grpcio
